gradio/__init__.py
gradio/analytics.py
gradio/blocks.py
gradio/components.py
gradio/context.py
gradio/data_classes.py
gradio/deprecation.py
gradio/events.py
gradio/exceptions.py
gradio/external.py
gradio/external_utils.py
gradio/flagging.py
gradio/helpers.py
gradio/inputs.py
gradio/interface.py
gradio/interpretation.py
gradio/ipython_ext.py
gradio/layouts.py
gradio/mix.py
gradio/networking.py
gradio/outputs.py
gradio/pipelines.py
gradio/processing_utils.py
gradio/queueing.py
gradio/ranged_response.py
gradio/reload.py
gradio/routes.py
gradio/strings.py
gradio/templates.py
gradio/tunneling.py
gradio/utils.py
gradio/version.txt
gradio/templates/frontend/favicon.png
gradio/templates/frontend/index.html
gradio/templates/frontend/assets/BlockLabel-d1434b3b.js
gradio/templates/frontend/assets/BlockLabel-d1434b3b.js.map
gradio/templates/frontend/assets/BlockTitle-11df09b3.js
gradio/templates/frontend/assets/BlockTitle-11df09b3.js.map
gradio/templates/frontend/assets/Blocks-9463a1f9.css
gradio/templates/frontend/assets/Blocks-ac631342.js
gradio/templates/frontend/assets/Blocks-ac631342.js.map
gradio/templates/frontend/assets/Button-4cd12e76.css
gradio/templates/frontend/assets/Button-d7d8a540.js
gradio/templates/frontend/assets/Button-d7d8a540.js.map
gradio/templates/frontend/assets/ColorPicker-76ff4dc7.css
gradio/templates/frontend/assets/ColorPicker.svelte_svelte_type_style_lang-700774cc.js.map
gradio/templates/frontend/assets/Column-2853eb31.css
gradio/templates/frontend/assets/Column-4c497891.js
gradio/templates/frontend/assets/Column-4c497891.js.map
gradio/templates/frontend/assets/Column.svelte_svelte_type_style_lang-bf454eb5.js.map
gradio/templates/frontend/assets/Copy-789f2249.js
gradio/templates/frontend/assets/Copy-789f2249.js.map
gradio/templates/frontend/assets/Download-c62274d7.js
gradio/templates/frontend/assets/Download-c62274d7.js.map
gradio/templates/frontend/assets/DropdownArrow-5fa4dd09.css
gradio_version_freeze-3.32.2.dist-info/METADATA
gradio_version_freeze-3.32.2.dist-info/WHEEL
gradio_version_freeze-3.32.2.dist-info/entry_points.txt
gradio_version_freeze-3.32.2.dist-info/licenses/LICENSE
gradio_version_freeze-3.32.2.dist-info/RECORD
